fsSignal/__init__.py
fsSignal/abcs.py
fsSignal/fsSignal.py
fsSignal/py.typed
python_fssignal-0.1.1.dist-info/LICENSE.md
python_fssignal-0.1.1.dist-info/METADATA
python_fssignal-0.1.1.dist-info/WHEEL
python_fssignal-0.1.1.dist-info/top_level.txt
python_fssignal-0.1.1.dist-info/RECORD
